[{"sgf":"http:\/\/files.gokgs.com\/games\/2010\/7\/23\/stuie-scotistic.sgf","white":"stuie [8k]","black":"scotistic [11k]","setup":"19\u00d719 H3","date":"July 23rd","result":"B+27.5"},{"sgf":"http:\/\/files.gokgs.com\/games\/2010\/7\/21\/dougd-scotistic.sgf","white":"dougd [9k]","black":"scotistic [11k]","setup":"19\u00d719 H2","date":"July 21st","result":"B+56.5"},{"sgf":"http:\/\/files.gokgs.com\/games\/2010\/7\/21\/nelu-scotistic.sgf","white":"nelu [11k]","black":"scotistic [11k]","setup":"19\u00d719 ","date":"July 21st","result":"W+0.5"},{"sgf":"http:\/\/files.gokgs.com\/games\/2010\/7\/21\/scotistic-jackgo2.sgf","white":"scotistic [11k]","black":"jackgo2 [11k]","setup":"19\u00d719 ","date":"July 21st","result":"W+Forf."},{"sgf":"http:\/\/files.gokgs.com\/games\/2010\/7\/21\/scotistic-mom.sgf","white":"scotistic [11k]","black":"mom [12k]","setup":"19\u00d719 ","date":"July 21st","result":"B+23.5"},{"sgf":"http:\/\/files.gokgs.com\/games\/2010\/7\/21\/axio-scotistic.sgf","white":"axio [10k]","black":"scotistic [11k]","setup":"19\u00d719 ","date":"July 21st","result":"W+Res."},{"sgf":"http:\/\/files.gokgs.com\/games\/2010\/7\/20\/xoffiy-scotistic.sgf","white":"xoffiy [11k]","black":"scotistic [11k]","setup":"19\u00d719 ","date":"July 20th","result":"B+7.5"},{"sgf":"http:\/\/files.gokgs.com\/games\/2010\/7\/20\/fbhooligan-scotistic.sgf","white":"fbhooligan [10k]","black":"scotistic [11k]","setup":"19\u00d719 ","date":"July 20th","result":"B+31.5"},{"sgf":"http:\/\/files.gokgs.com\/games\/2010\/7\/19\/scotistic-JeanV.sgf","white":"scotistic [11k]","black":"JeanV [11k]","setup":"19\u00d719 ","date":"July 19th","result":"W+Res."},{"sgf":"http:\/\/files.gokgs.com\/games\/2010\/7\/19\/Ptitommo-scotistic.sgf","white":"Ptitommo [9k]","black":"scotistic [11k]","setup":"19\u00d719 H2","date":"July 19th","result":"W+Res."},{"sgf":"http:\/\/files.gokgs.com\/games\/2010\/7\/19\/oolongtea-scotistic.sgf","white":"oolongtea [7k]","black":"scotistic [11k]","setup":"19\u00d719 H4","date":"July 19th","result":"W+Res."},{"sgf":"http:\/\/files.gokgs.com\/games\/2010\/7\/19\/scotistic-ghytre.sgf","white":"scotistic [11k]","black":"ghytre [14k]","setup":"19\u00d719 H3","date":"July 19th","result":"B+22.5"},{"sgf":"http:\/\/files.gokgs.com\/games\/2010\/7\/17\/scotistic-alson.sgf","white":"scotistic [11k]","black":"alson [13k]","setup":"19\u00d719 ","date":"July 17th","result":"W+48.5"},{"sgf":"http:\/\/files.gokgs.com\/games\/2010\/7\/17\/scotistic-guinou.sgf","white":"scotistic [11k]","black":"guinou [13k]","setup":"19\u00d719 H2","date":"July 17th","result":"W+Res."},{"sgf":"http:\/\/files.gokgs.com\/games\/2010\/7\/17\/XB40-scotistic.sgf","white":"XB40 [10k]","black":"scotistic [11k]","setup":"19\u00d719 ","date":"July 17th","result":"W+Res."},{"sgf":"http:\/\/files.gokgs.com\/games\/2010\/7\/17\/icerun-scotistic.sgf","white":"icerun","black":"scotistic [11k]","setup":"19\u00d719 H9","date":"July 17th","result":"B+Time"},{"sgf":"http:\/\/files.gokgs.com\/games\/2010\/7\/16\/scotistic-pitbear.sgf","white":"scotistic [11k]","black":"pitbear [12k]","setup":"19\u00d719 ","date":"July 16th","result":"B+Res."},{"sgf":"http:\/\/files.gokgs.com\/games\/2010\/7\/15\/scotistic-mareck.sgf","white":"scotistic [11k]","black":"mareck [12k?]","setup":"9\u00d79 ","date":"July 15th","result":"W+1.5"},{"sgf":"http:\/\/files.gokgs.com\/games\/2010\/7\/15\/scotistic-aieie.sgf","white":"scotistic [11k]","black":"aieie [11k]","setup":"19\u00d719 ","date":"July 15th","result":"W+Res."},{"sgf":"http:\/\/files.gokgs.com\/games\/2010\/7\/14\/atari64-scotistic.sgf","white":"atari64 [10k]","black":"scotistic [11k]","setup":"19\u00d719 ","date":"July 14th","result":"W+47.5"},{"sgf":"http:\/\/files.gokgs.com\/games\/2010\/7\/13\/scotistic-good2013.sgf","white":"scotistic [11k]","black":"good2013 [12k]","setup":"19\u00d719 ","date":"July 13th","result":"W+Res."},{"sgf":"http:\/\/files.gokgs.com\/games\/2010\/7\/13\/scotistic-StariOskol.sgf","white":"scotistic [11k]","black":"StariOskol [-]","setup":"19\u00d719 ","date":"July 13th","result":"B+56.5"},{"sgf":"http:\/\/files.gokgs.com\/games\/2010\/7\/13\/scotistic-mleamer.sgf","white":"scotistic [11k]","black":"mleamer [12k]","setup":"19\u00d719 ","date":"July 13th","result":"W+26.5"},{"sgf":"http:\/\/files.gokgs.com\/games\/2010\/7\/12\/scotistic-pitbear.sgf","white":"scotistic [11k]","black":"pitbear [12k]","setup":"19\u00d719 ","date":"July 12th","result":"B+26.5"},{"sgf":"http:\/\/files.gokgs.com\/games\/2010\/7\/12\/Niceday12-scotistic.sgf","white":"Niceday12","black":"scotistic [11k]","setup":"19\u00d719 ","date":"July 12th","result":"W+Res."},{"sgf":"http:\/\/files.gokgs.com\/games\/2010\/7\/10\/hortensie-scotistic.sgf","white":"hortensie [11k]","black":"scotistic [11k]","setup":"19\u00d719 ","date":"July 10th","result":"B+18.5"},{"sgf":"http:\/\/files.gokgs.com\/games\/2010\/7\/9\/scotistic-happylife.sgf","white":"scotistic [12k]","black":"happylife [13k]","setup":"19\u00d719 ","date":"July 9th","result":"W+Forf."},{"sgf":"http:\/\/files.gokgs.com\/games\/2010\/7\/9\/doublepass-scotistic.sgf","white":"doublepass [9k]","black":"scotistic [12k]","setup":"19\u00d719 H3","date":"July 9th","result":"W+36.5"},{"sgf":"http:\/\/files.gokgs.com\/games\/2010\/7\/8\/scotistic-helioske.sgf","white":"scotistic [12k]","black":"helioske [13k]","setup":"19\u00d719 ","date":"July 8th","result":"W+29.5"},{"sgf":"http:\/\/files.gokgs.com\/games\/2010\/7\/8\/scotistic-oaquili.sgf","white":"scotistic [12k]","black":"oaquili [13k]","setup":"19\u00d719 ","date":"July 8th","result":"W+53.5"}]